[
    {
        "regionId": 31,
        "township": "",
        "name": "Baldovinesti",
        "isActive": 1
    },
    {
        "regionId": 31,
        "township": "",
        "name": "Bals",
        "isActive": 1
    },
    {
        "regionId": 31,
        "township": "",
        "name": "Bobicesti",
        "isActive": 1
    },
    {
        "regionId": 31,
        "township": "",
        "name": "Brastavatu",
        "isActive": 1
    },
    {
        "regionId": 31,
        "township": "",
        "name": "Brebeni",
        "isActive": 1
    },
    {
        "regionId": 31,
        "township": "",
        "name": "Brancoveni",
        "isActive": 1
    },
    {
        "regionId": 31,
        "township": "",
        "name": "Bucinisu",
        "isActive": 1
    },
    {
        "regionId": 31,
        "township": "",
        "name": "Barza",
        "isActive": 1
    },
    {
        "regionId": 31,
        "township": "",
        "name": "Babiciu",
        "isActive": 1
    },
    {
        "regionId": 31,
        "township": "",
        "name": "Caracal",
        "isActive": 1
    },
    {
        "regionId": 31,
        "township": "",
        "name": "Cezieni",
        "isActive": 1
    },
    {
        "regionId": 31,
        "township": "",
        "name": "Cilieni",
        "isActive": 1
    },
    {
        "regionId": 31,
        "township": "",
        "name": "Colonesti",
        "isActive": 1
    },
    {
        "regionId": 31,
        "township": "",
        "name": "Corabia",
        "isActive": 1
    },
    {
        "regionId": 31,
        "township": "",
        "name": "Corbu",
        "isActive": 1
    },
    {
        "regionId": 31,
        "township": "",
        "name": "Coteana",
        "isActive": 1
    },
    {
        "regionId": 31,
        "township": "",
        "name": "Crampoia",
        "isActive": 1
    },
    {
        "regionId": 31,
        "township": "",
        "name": "Cungrea",
        "isActive": 1
    },
    {
        "regionId": 31,
        "township": "",
        "name": "Curtisoara",
        "isActive": 1
    },
    {
        "regionId": 31,
        "township": "",
        "name": "Carlogani",
        "isActive": 1
    },
    {
        "regionId": 31,
        "township": "",
        "name": "Deveselu",
        "isActive": 1
    },
    {
        "regionId": 31,
        "township": "",
        "name": "Dobretu",
        "isActive": 1
    },
    {
        "regionId": 31,
        "township": "",
        "name": "Dobrosloveni",
        "isActive": 1
    },
    {
        "regionId": 31,
        "township": "",
        "name": "Dobroteasa",
        "isActive": 1
    },
    {
        "regionId": 31,
        "township": "",
        "name": "Dobrun",
        "isActive": 1
    },
    {
        "regionId": 31,
        "township": "",
        "name": "Draghiceni",
        "isActive": 1
    },
    {
        "regionId": 31,
        "township": "",
        "name": "Draganesti-Olt",
        "isActive": 1
    },
    {
        "regionId": 31,
        "township": "",
        "name": "Daneasa",
        "isActive": 1
    },
    {
        "regionId": 31,
        "township": "",
        "name": "Fagetelu",
        "isActive": 1
    },
    {
        "regionId": 31,
        "township": "",
        "name": "Falcoiu",
        "isActive": 1
    },
    {
        "regionId": 31,
        "township": "",
        "name": "Farcasele",
        "isActive": 1
    },
    {
        "regionId": 31,
        "township": "",
        "name": "Giuvarasti",
        "isActive": 1
    },
    {
        "regionId": 31,
        "township": "",
        "name": "Gostavatu",
        "isActive": 1
    },
    {
        "regionId": 31,
        "township": "",
        "name": "Grojdibodu",
        "isActive": 1
    },
    {
        "regionId": 31,
        "township": "",
        "name": "Gradinari",
        "isActive": 1
    },
    {
        "regionId": 31,
        "township": "",
        "name": "Garcov",
        "isActive": 1
    },
    {
        "regionId": 31,
        "township": "",
        "name": "Ganeasa",
        "isActive": 1
    },
    {
        "regionId": 31,
        "township": "",
        "name": "Ianca",
        "isActive": 1
    },
    {
        "regionId": 31,
        "township": "",
        "name": "Iancu Jianu",
        "isActive": 1
    },
    {
        "regionId": 31,
        "township": "",
        "name": "Icoana",
        "isActive": 1
    },
    {
        "regionId": 31,
        "township": "",
        "name": "Izbiceni",
        "isActive": 1
    },
    {
        "regionId": 31,
        "township": "",
        "name": "Izvoarele",
        "isActive": 1
    },
    {
        "regionId": 31,
        "township": "",
        "name": "Leleasca",
        "isActive": 1
    },
    {
        "regionId": 31,
        "township": "",
        "name": "Mihaesti",
        "isActive": 1
    },
    {
        "regionId": 31,
        "township": "",
        "name": "Morunglav",
        "isActive": 1
    },
    {
        "regionId": 31,
        "township": "",
        "name": "Movileni",
        "isActive": 1
    },
    {
        "regionId": 31,
        "township": "",
        "name": "Maruntei",
        "isActive": 1
    },
    {
        "regionId": 31,
        "township": "",
        "name": "Nicolae Titulescu",
        "isActive": 1
    },
    {
        "regionId": 31,
        "township": "",
        "name": "Oboga",
        "isActive": 1
    },
    {
        "regionId": 31,
        "township": "",
        "name": "Obarsia",
        "isActive": 1
    },
    {
        "regionId": 31,
        "township": "",
        "name": "Oporelu",
        "isActive": 1
    },
    {
        "regionId": 31,
        "township": "",
        "name": "Orlea",
        "isActive": 1
    },
    {
        "regionId": 31,
        "township": "",
        "name": "Osica de Sus",
        "isActive": 1
    },
    {
        "regionId": 31,
        "township": "",
        "name": "Perieti",
        "isActive": 1
    },
    {
        "regionId": 31,
        "township": "",
        "name": "Piatra-Olt",
        "isActive": 1
    },
    {
        "regionId": 31,
        "township": "",
        "name": "Plesoiu",
        "isActive": 1
    },
    {
        "regionId": 31,
        "township": "",
        "name": "Poboru",
        "isActive": 1
    },
    {
        "regionId": 31,
        "township": "",
        "name": "Potcoava",
        "isActive": 1
    },
    {
        "regionId": 31,
        "township": "",
        "name": "Priseaca",
        "isActive": 1
    },
    {
        "regionId": 31,
        "township": "",
        "name": "Radomiresti",
        "isActive": 1
    },
    {
        "regionId": 31,
        "township": "",
        "name": "Redea",
        "isActive": 1
    },
    {
        "regionId": 31,
        "township": "",
        "name": "Rotunda",
        "isActive": 1
    },
    {
        "regionId": 31,
        "township": "",
        "name": "Rusanesti",
        "isActive": 1
    },
    {
        "regionId": 31,
        "township": "",
        "name": "Schitu",
        "isActive": 1
    },
    {
        "regionId": 31,
        "township": "",
        "name": "Scornicesti",
        "isActive": 1
    },
    {
        "regionId": 31,
        "township": "",
        "name": "Scarisoara",
        "isActive": 1
    },
    {
        "regionId": 31,
        "township": "",
        "name": "Seaca",
        "isActive": 1
    },
    {
        "regionId": 31,
        "township": "",
        "name": "Slatina",
        "isActive": 1
    },
    {
        "regionId": 31,
        "township": "",
        "name": "Slatioara",
        "isActive": 1
    },
    {
        "regionId": 31,
        "township": "",
        "name": "Spineni",
        "isActive": 1
    },
    {
        "regionId": 31,
        "township": "",
        "name": "Sprancenata",
        "isActive": 1
    },
    {
        "regionId": 31,
        "township": "",
        "name": "Stoenesti",
        "isActive": 1
    },
    {
        "regionId": 31,
        "township": "",
        "name": "Stoicanesti",
        "isActive": 1
    },
    {
        "regionId": 31,
        "township": "",
        "name": "Strejesti",
        "isActive": 1
    },
    {
        "regionId": 31,
        "township": "",
        "name": "Studina",
        "isActive": 1
    },
    {
        "regionId": 31,
        "township": "",
        "name": "Samburesti",
        "isActive": 1
    },
    {
        "regionId": 31,
        "township": "",
        "name": "Teslui",
        "isActive": 1
    },
    {
        "regionId": 31,
        "township": "",
        "name": "Tia Mare",
        "isActive": 1
    },
    {
        "regionId": 31,
        "township": "",
        "name": "Topana",
        "isActive": 1
    },
    {
        "regionId": 31,
        "township": "",
        "name": "Traian",
        "isActive": 1
    },
    {
        "regionId": 31,
        "township": "",
        "name": "Tufeni",
        "isActive": 1
    },
    {
        "regionId": 31,
        "township": "",
        "name": "Tatulesti",
        "isActive": 1
    },
    {
        "regionId": 31,
        "township": "",
        "name": "Urzica",
        "isActive": 1
    },
    {
        "regionId": 31,
        "township": "",
        "name": "Valea Mare",
        "isActive": 1
    },
    {
        "regionId": 31,
        "township": "",
        "name": "Verguleasa",
        "isActive": 1
    },
    {
        "regionId": 31,
        "township": "",
        "name": "Vitomiresti",
        "isActive": 1
    },
    {
        "regionId": 31,
        "township": "",
        "name": "Visina",
        "isActive": 1
    },
    {
        "regionId": 31,
        "township": "",
        "name": "Vladila",
        "isActive": 1
    },
    {
        "regionId": 31,
        "township": "",
        "name": "Voineasa",
        "isActive": 1
    },
    {
        "regionId": 31,
        "township": "",
        "name": "Vulpeni",
        "isActive": 1
    },
    {
        "regionId": 31,
        "township": "",
        "name": "Vulturesti",
        "isActive": 1
    },
    {
        "regionId": 31,
        "township": "",
        "name": "Valcele",
        "isActive": 1
    },
    {
        "regionId": 31,
        "township": "",
        "name": "Vadastra",
        "isActive": 1
    },
    {
        "regionId": 31,
        "township": "",
        "name": "Vadastrita",
        "isActive": 1
    },
    {
        "regionId": 31,
        "township": "",
        "name": "Valeni",
        "isActive": 1
    },
    {
        "regionId": 31,
        "township": "",
        "name": "Serbanesti",
        "isActive": 1
    },
    {
        "regionId": 31,
        "township": "",
        "name": "Stefan cel Mare",
        "isActive": 1
    },
    {
        "regionId": 31,
        "township": "Baldovinesti",
        "name": "Brosteni",
        "isActive": 1
    },
    {
        "regionId": 31,
        "township": "Baldovinesti",
        "name": "Baleasa",
        "isActive": 1
    },
    {
        "regionId": 31,
        "township": "Baldovinesti",
        "name": "Damburile",
        "isActive": 1
    },
    {
        "regionId": 31,
        "township": "Baldovinesti",
        "name": "Gubandru",
        "isActive": 1
    },
    {
        "regionId": 31,
        "township": "Baldovinesti",
        "name": "Gavanesti",
        "isActive": 1
    },
    {
        "regionId": 31,
        "township": "Baldovinesti",
        "name": "Pietris",
        "isActive": 1
    },
    {
        "regionId": 31,
        "township": "Bals",
        "name": "Corbeni",
        "isActive": 1
    },
    {
        "regionId": 31,
        "township": "Bals",
        "name": "Romana",
        "isActive": 1
    },
    {
        "regionId": 31,
        "township": "Bals",
        "name": "Teis",
        "isActive": 1
    },
    {
        "regionId": 31,
        "township": "Barasti",
        "name": "Boroesti",
        "isActive": 1
    },
    {
        "regionId": 31,
        "township": "Barasti",
        "name": "Barastii de Cepturi",
        "isActive": 1
    },
    {
        "regionId": 31,
        "township": "Barasti",
        "name": "Barastii de Vede",
        "isActive": 1
    },
    {
        "regionId": 31,
        "township": "Barasti",
        "name": "Ciocanesti",
        "isActive": 1
    },
    {
        "regionId": 31,
        "township": "Barasti",
        "name": "Lazaresti",
        "isActive": 1
    },
    {
        "regionId": 31,
        "township": "Barasti",
        "name": "Mereni",
        "isActive": 1
    },
    {
        "regionId": 31,
        "township": "Barasti",
        "name": "Motoesti",
        "isActive": 1
    },
    {
        "regionId": 31,
        "township": "Barasti",
        "name": "Popesti",
        "isActive": 1
    },
    {
        "regionId": 31,
        "township": "Barza",
        "name": "Branet",
        "isActive": 1
    },
    {
        "regionId": 31,
        "township": "Bobicesti",
        "name": "Bechet",
        "isActive": 1
    },
    {
        "regionId": 31,
        "township": "Bobicesti",
        "name": "Belgun",
        "isActive": 1
    },
    {
        "regionId": 31,
        "township": "Bobicesti",
        "name": "Chintesti",
        "isActive": 1
    },
    {
        "regionId": 31,
        "township": "Bobicesti",
        "name": "Comanesti",
        "isActive": 1
    },
    {
        "regionId": 31,
        "township": "Bobicesti",
        "name": "Govora",
        "isActive": 1
    },
    {
        "regionId": 31,
        "township": "Bobicesti",
        "name": "Leotesti",
        "isActive": 1
    },
    {
        "regionId": 31,
        "township": "Bobicesti",
        "name": "Mirila",
        "isActive": 1
    },
    {
        "regionId": 31,
        "township": "Brancoveni",
        "name": "Margheni",
        "isActive": 1
    },
    {
        "regionId": 31,
        "township": "Brancoveni",
        "name": "Ociogi",
        "isActive": 1
    },
    {
        "regionId": 31,
        "township": "Brancoveni",
        "name": "Valeni",
        "isActive": 1
    },
    {
        "regionId": 31,
        "township": "Brastavatu",
        "name": "Crusovu",
        "isActive": 1
    },
    {
        "regionId": 31,
        "township": "Brebeni",
        "name": "Teiusu",
        "isActive": 1
    },
    {
        "regionId": 31,
        "township": "Bucinisu",
        "name": "Bucinisu Mic",
        "isActive": 1
    },
    {
        "regionId": 31,
        "township": "Carlogani",
        "name": "Beculesti",
        "isActive": 1
    },
    {
        "regionId": 31,
        "township": "Carlogani",
        "name": "Cepari",
        "isActive": 1
    },
    {
        "regionId": 31,
        "township": "Carlogani",
        "name": "Scorbura",
        "isActive": 1
    },
    {
        "regionId": 31,
        "township": "Carlogani",
        "name": "Stupina",
        "isActive": 1
    },
    {
        "regionId": 31,
        "township": "Cezieni",
        "name": "Bondrea",
        "isActive": 1
    },
    {
        "regionId": 31,
        "township": "Cezieni",
        "name": "Corlatesti",
        "isActive": 1
    },
    {
        "regionId": 31,
        "township": "Colonesti",
        "name": "Barasti",
        "isActive": 1
    },
    {
        "regionId": 31,
        "township": "Colonesti",
        "name": "Batareni",
        "isActive": 1
    },
    {
        "regionId": 31,
        "township": "Colonesti",
        "name": "Chelbesti",
        "isActive": 1
    },
    {
        "regionId": 31,
        "township": "Colonesti",
        "name": "Carstani",
        "isActive": 1
    },
    {
        "regionId": 31,
        "township": "Colonesti",
        "name": "Guesti",
        "isActive": 1
    },
    {
        "regionId": 31,
        "township": "Colonesti",
        "name": "Maruntei",
        "isActive": 1
    },
    {
        "regionId": 31,
        "township": "Colonesti",
        "name": "Navargeni",
        "isActive": 1
    },
    {
        "regionId": 31,
        "township": "Colonesti",
        "name": "Vlaici",
        "isActive": 1
    },
    {
        "regionId": 31,
        "township": "Corabia",
        "name": "Tudor Vladimirescu",
        "isActive": 1
    },
    {
        "regionId": 31,
        "township": "Corabia",
        "name": "Vartopu",
        "isActive": 1
    },
    {
        "regionId": 31,
        "township": "Corbu",
        "name": "Burdulesti",
        "isActive": 1
    },
    {
        "regionId": 31,
        "township": "Corbu",
        "name": "Buzesti",
        "isActive": 1
    },
    {
        "regionId": 31,
        "township": "Corbu",
        "name": "Ciuresti",
        "isActive": 1
    },
    {
        "regionId": 31,
        "township": "Corbu",
        "name": "Milcoveni",
        "isActive": 1
    },
    {
        "regionId": 31,
        "township": "Crampoia",
        "name": "Buta",
        "isActive": 1
    },
    {
        "regionId": 31,
        "township": "Cungrea",
        "name": "Cepesti",
        "isActive": 1
    },
    {
        "regionId": 31,
        "township": "Cungrea",
        "name": "Ibanesti",
        "isActive": 1
    },
    {
        "regionId": 31,
        "township": "Cungrea",
        "name": "Miesti",
        "isActive": 1
    },
    {
        "regionId": 31,
        "township": "Cungrea",
        "name": "Otestii de Jos",
        "isActive": 1
    },
    {
        "regionId": 31,
        "township": "Cungrea",
        "name": "Otestii de Sus",
        "isActive": 1
    },
    {
        "regionId": 31,
        "township": "Cungrea",
        "name": "Spataru",
        "isActive": 1
    },
    {
        "regionId": 31,
        "township": "Curtisoara",
        "name": "Dobrotinet",
        "isActive": 1
    },
    {
        "regionId": 31,
        "township": "Curtisoara",
        "name": "Linia din Vale",
        "isActive": 1
    },
    {
        "regionId": 31,
        "township": "Curtisoara",
        "name": "Pietrisu",
        "isActive": 1
    },
    {
        "regionId": 31,
        "township": "Curtisoara",
        "name": "Proaspeti",
        "isActive": 1
    },
    {
        "regionId": 31,
        "township": "Curtisoara",
        "name": "Raitiu",
        "isActive": 1
    },
    {
        "regionId": 31,
        "township": "Daneasa",
        "name": "Berindei",
        "isActive": 1
    },
    {
        "regionId": 31,
        "township": "Daneasa",
        "name": "Cioflanu",
        "isActive": 1
    },
    {
        "regionId": 31,
        "township": "Daneasa",
        "name": "Pestra",
        "isActive": 1
    },
    {
        "regionId": 31,
        "township": "Daneasa",
        "name": "Zanoaga",
        "isActive": 1
    },
    {
        "regionId": 31,
        "township": "Deveselu",
        "name": "Comanca",
        "isActive": 1
    },
    {
        "regionId": 31,
        "township": "Dobretu",
        "name": "Curtisoara",
        "isActive": 1
    },
    {
        "regionId": 31,
        "township": "Dobretu",
        "name": "Horezu",
        "isActive": 1
    },
    {
        "regionId": 31,
        "township": "Dobrosloveni",
        "name": "Frasinetu",
        "isActive": 1
    },
    {
        "regionId": 31,
        "township": "Dobrosloveni",
        "name": "Potopinu",
        "isActive": 1
    },
    {
        "regionId": 31,
        "township": "Dobrosloveni",
        "name": "Resca",
        "isActive": 1
    },
    {
        "regionId": 31,
        "township": "Dobrosloveni",
        "name": "Rescuta",
        "isActive": 1
    },
    {
        "regionId": 31,
        "township": "Dobroteasa",
        "name": "Batia",
        "isActive": 1
    },
    {
        "regionId": 31,
        "township": "Dobroteasa",
        "name": "Campu Mare",
        "isActive": 1
    },
    {
        "regionId": 31,
        "township": "Dobroteasa",
        "name": "Vulpesti",
        "isActive": 1
    },
    {
        "regionId": 31,
        "township": "Dobrun",
        "name": "Bobu",
        "isActive": 1
    },
    {
        "regionId": 31,
        "township": "Dobrun",
        "name": "Chilii",
        "isActive": 1
    },
    {
        "regionId": 31,
        "township": "Dobrun",
        "name": "Osica de Jos",
        "isActive": 1
    },
    {
        "regionId": 31,
        "township": "Dobrun",
        "name": "Rosienii Mari",
        "isActive": 1
    },
    {
        "regionId": 31,
        "township": "Dobrun",
        "name": "Rosienii Mici",
        "isActive": 1
    },
    {
        "regionId": 31,
        "township": "Dobrun",
        "name": "Ulmet",
        "isActive": 1
    },
    {
        "regionId": 31,
        "township": "Draganesti-Olt",
        "name": "Comani",
        "isActive": 1
    },
    {
        "regionId": 31,
        "township": "Draghiceni",
        "name": "Grozavesti",
        "isActive": 1
    },
    {
        "regionId": 31,
        "township": "Draghiceni",
        "name": "Liiceni",
        "isActive": 1
    },
    {
        "regionId": 31,
        "township": "Fagetelu",
        "name": "Bagesti",
        "isActive": 1
    },
    {
        "regionId": 31,
        "township": "Fagetelu",
        "name": "Chilia",
        "isActive": 1
    },
    {
        "regionId": 31,
        "township": "Fagetelu",
        "name": "Gruiu",
        "isActive": 1
    },
    {
        "regionId": 31,
        "township": "Fagetelu",
        "name": "Isaci",
        "isActive": 1
    },
    {
        "regionId": 31,
        "township": "Fagetelu",
        "name": "Pielcani",
        "isActive": 1
    },
    {
        "regionId": 31,
        "township": "Falcoiu",
        "name": "Cioroiasu",
        "isActive": 1
    },
    {
        "regionId": 31,
        "township": "Falcoiu",
        "name": "Cioroiu",
        "isActive": 1
    },
    {
        "regionId": 31,
        "township": "Farcasele",
        "name": "Farcasu de Jos",
        "isActive": 1
    },
    {
        "regionId": 31,
        "township": "Farcasele",
        "name": "Ghimpati",
        "isActive": 1
    },
    {
        "regionId": 31,
        "township": "Farcasele",
        "name": "Hotarani",
        "isActive": 1
    },
    {
        "regionId": 31,
        "township": "Ganeasa",
        "name": "Dranovatu",
        "isActive": 1
    },
    {
        "regionId": 31,
        "township": "Ganeasa",
        "name": "Gradistea",
        "isActive": 1
    },
    {
        "regionId": 31,
        "township": "Ganeasa",
        "name": "Izvoru",
        "isActive": 1
    },
    {
        "regionId": 31,
        "township": "Ganeasa",
        "name": "Oltisoru",
        "isActive": 1
    },
    {
        "regionId": 31,
        "township": "Garcov",
        "name": "Ursa",
        "isActive": 1
    },
    {
        "regionId": 31,
        "township": "Gostavatu",
        "name": "Slaveni",
        "isActive": 1
    },
    {
        "regionId": 31,
        "township": "Gradinari",
        "name": "Petculesti",
        "isActive": 1
    },
    {
        "regionId": 31,
        "township": "Gradinari",
        "name": "Runcu Mare",
        "isActive": 1
    },
    {
        "regionId": 31,
        "township": "Gradinari",
        "name": "Satu Nou",
        "isActive": 1
    },
    {
        "regionId": 31,
        "township": "Grojdibodu",
        "name": "Hotaru",
        "isActive": 1
    },
    {
        "regionId": 31,
        "township": "Ianca",
        "name": "Potelu",
        "isActive": 1
    },
    {
        "regionId": 31,
        "township": "Iancu Jianu",
        "name": "Dobriceni",
        "isActive": 1
    },
    {
        "regionId": 31,
        "township": "Iancu Jianu",
        "name": "Preotesti",
        "isActive": 1
    },
    {
        "regionId": 31,
        "township": "Icoana",
        "name": "Floru",
        "isActive": 1
    },
    {
        "regionId": 31,
        "township": "Icoana",
        "name": "Ursoaia",
        "isActive": 1
    },
    {
        "regionId": 31,
        "township": "Izvoarele",
        "name": "Alimanesti",
        "isActive": 1
    },
    {
        "regionId": 31,
        "township": "Leleasca",
        "name": "Afumati",
        "isActive": 1
    },
    {
        "regionId": 31,
        "township": "Leleasca",
        "name": "Greeresti",
        "isActive": 1
    },
    {
        "regionId": 31,
        "township": "Leleasca",
        "name": "Mierlicesti",
        "isActive": 1
    },
    {
        "regionId": 31,
        "township": "Leleasca",
        "name": "Tonesti",
        "isActive": 1
    },
    {
        "regionId": 31,
        "township": "Leleasca",
        "name": "Tufaru",
        "isActive": 1
    },
    {
        "regionId": 31,
        "township": "Leleasca",
        "name": "Ursi",
        "isActive": 1
    },
    {
        "regionId": 31,
        "township": "Maruntei",
        "name": "Balanesti",
        "isActive": 1
    },
    {
        "regionId": 31,
        "township": "Maruntei",
        "name": "Malu Rosu",
        "isActive": 1
    },
    {
        "regionId": 31,
        "township": "Mihaesti",
        "name": "Busca",
        "isActive": 1
    },
    {
        "regionId": 31,
        "township": "Milcov",
        "name": "Ipotesti",
        "isActive": 1
    },
    {
        "regionId": 31,
        "township": "Milcov",
        "name": "Milcovu din Deal",
        "isActive": 1
    },
    {
        "regionId": 31,
        "township": "Milcov",
        "name": "Milcovu din Vale",
        "isActive": 1
    },
    {
        "regionId": 31,
        "township": "Milcov",
        "name": "Stejaru",
        "isActive": 1
    },
    {
        "regionId": 31,
        "township": "Milcov",
        "name": "Ulmi",
        "isActive": 1
    },
    {
        "regionId": 31,
        "township": "Morunglav",
        "name": "Barasti",
        "isActive": 1
    },
    {
        "regionId": 31,
        "township": "Morunglav",
        "name": "Ghiosani",
        "isActive": 1
    },
    {
        "regionId": 31,
        "township": "Morunglav",
        "name": "Morunesti",
        "isActive": 1
    },
    {
        "regionId": 31,
        "township": "Morunglav",
        "name": "Poiana Mare",
        "isActive": 1
    },
    {
        "regionId": 31,
        "township": "Movileni",
        "name": "Bacea",
        "isActive": 1
    },
    {
        "regionId": 31,
        "township": "Nicolae Titulescu",
        "name": "Ghimpeteni",
        "isActive": 1
    },
    {
        "regionId": 31,
        "township": "Nicolae Titulescu",
        "name": "Ghimpetenii Noi",
        "isActive": 1
    },
    {
        "regionId": 31,
        "township": "Obarsia",
        "name": "Coteni",
        "isActive": 1
    },
    {
        "regionId": 31,
        "township": "Obarsia",
        "name": "Campu Parului",
        "isActive": 1
    },
    {
        "regionId": 31,
        "township": "Obarsia",
        "name": "Obarsia Noua",
        "isActive": 1
    },
    {
        "regionId": 31,
        "township": "Obarsia",
        "name": "Tabonu",
        "isActive": 1
    },
    {
        "regionId": 31,
        "township": "Oboga",
        "name": "Calui",
        "isActive": 1
    },
    {
        "regionId": 31,
        "township": "Oboga",
        "name": "Gura Caluiu",
        "isActive": 1
    },
    {
        "regionId": 31,
        "township": "Oporelu",
        "name": "Beria de Jos",
        "isActive": 1
    },
    {
        "regionId": 31,
        "township": "Oporelu",
        "name": "Beria de Sus",
        "isActive": 1
    },
    {
        "regionId": 31,
        "township": "Oporelu",
        "name": "Radesti",
        "isActive": 1
    },
    {
        "regionId": 31,
        "township": "Optasi-Magura",
        "name": "Optasi",
        "isActive": 1
    },
    {
        "regionId": 31,
        "township": "Optasi-Magura",
        "name": "Vitanesti",
        "isActive": 1
    },
    {
        "regionId": 31,
        "township": "Orlea",
        "name": "Gura Padinii",
        "isActive": 1
    },
    {
        "regionId": 31,
        "township": "Orlea",
        "name": "Orlea Noua",
        "isActive": 1
    },
    {
        "regionId": 31,
        "township": "Orlea",
        "name": "Satu Nou",
        "isActive": 1
    },
    {
        "regionId": 31,
        "township": "Osica De Sus",
        "name": "Greci",
        "isActive": 1
    },
    {
        "regionId": 31,
        "township": "Osica De Sus",
        "name": "Ostrov",
        "isActive": 1
    },
    {
        "regionId": 31,
        "township": "Osica De Sus",
        "name": "Peretu",
        "isActive": 1
    },
    {
        "regionId": 31,
        "township": "Osica De Sus",
        "name": "Tomeni",
        "isActive": 1
    },
    {
        "regionId": 31,
        "township": "Osica De Sus",
        "name": "Vladuleni",
        "isActive": 1
    },
    {
        "regionId": 31,
        "township": "Parscoveni",
        "name": "Butoi",
        "isActive": 1
    },
    {
        "regionId": 31,
        "township": "Parscoveni",
        "name": "Olari",
        "isActive": 1
    },
    {
        "regionId": 31,
        "township": "Parscoveni",
        "name": "Parscoveni",
        "isActive": 1
    },
    {
        "regionId": 31,
        "township": "Parscoveni",
        "name": "Soparlita",
        "isActive": 1
    },
    {
        "regionId": 31,
        "township": "Perieti",
        "name": "Balteni",
        "isActive": 1
    },
    {
        "regionId": 31,
        "township": "Perieti",
        "name": "Mierlestii de Sus",
        "isActive": 1
    },
    {
        "regionId": 31,
        "township": "Perieti",
        "name": "Magura",
        "isActive": 1
    },
    {
        "regionId": 31,
        "township": "Piatra-Olt",
        "name": "Bistrita Noua",
        "isActive": 1
    },
    {
        "regionId": 31,
        "township": "Piatra-Olt",
        "name": "Criva de Jos",
        "isActive": 1
    },
    {
        "regionId": 31,
        "township": "Piatra-Olt",
        "name": "Criva de Sus",
        "isActive": 1
    },
    {
        "regionId": 31,
        "township": "Piatra-Olt",
        "name": "Enosesti",
        "isActive": 1
    },
    {
        "regionId": 31,
        "township": "Piatra-Olt",
        "name": "Piatra",
        "isActive": 1
    },
    {
        "regionId": 31,
        "township": "Plesoiu",
        "name": "Arcesti",
        "isActive": 1
    },
    {
        "regionId": 31,
        "township": "Plesoiu",
        "name": "Arcesti Cot",
        "isActive": 1
    },
    {
        "regionId": 31,
        "township": "Plesoiu",
        "name": "Cocorasti",
        "isActive": 1
    },
    {
        "regionId": 31,
        "township": "Plesoiu",
        "name": "Doba",
        "isActive": 1
    },
    {
        "regionId": 31,
        "township": "Plesoiu",
        "name": "Schitu din Deal",
        "isActive": 1
    },
    {
        "regionId": 31,
        "township": "Plesoiu",
        "name": "Schitu din Vale",
        "isActive": 1
    },
    {
        "regionId": 31,
        "township": "Poboru",
        "name": "Albesti",
        "isActive": 1
    },
    {
        "regionId": 31,
        "township": "Poboru",
        "name": "Cornatelu",
        "isActive": 1
    },
    {
        "regionId": 31,
        "township": "Poboru",
        "name": "Creti",
        "isActive": 1
    },
    {
        "regionId": 31,
        "township": "Poboru",
        "name": "Seaca",
        "isActive": 1
    },
    {
        "regionId": 31,
        "township": "Poboru",
        "name": "Surpeni",
        "isActive": 1
    },
    {
        "regionId": 31,
        "township": "Potcoava",
        "name": "Potcoava Falcoeni",
        "isActive": 1
    },
    {
        "regionId": 31,
        "township": "Potcoava",
        "name": "Sinesti",
        "isActive": 1
    },
    {
        "regionId": 31,
        "township": "Potcoava",
        "name": "Trufinesti",
        "isActive": 1
    },
    {
        "regionId": 31,
        "township": "Potcoava",
        "name": "Valea Merilor",
        "isActive": 1
    },
    {
        "regionId": 31,
        "township": "Priseaca",
        "name": "Buicesti",
        "isActive": 1
    },
    {
        "regionId": 31,
        "township": "Priseaca",
        "name": "Saltanesti",
        "isActive": 1
    },
    {
        "regionId": 31,
        "township": "Radomiresti",
        "name": "Craciunei",
        "isActive": 1
    },
    {
        "regionId": 31,
        "township": "Radomiresti",
        "name": "Calinesti",
        "isActive": 1
    },
    {
        "regionId": 31,
        "township": "Radomiresti",
        "name": "Poiana",
        "isActive": 1
    },
    {
        "regionId": 31,
        "township": "Redea",
        "name": "Redisoara",
        "isActive": 1
    },
    {
        "regionId": 31,
        "township": "Redea",
        "name": "Valea Soarelui",
        "isActive": 1
    },
    {
        "regionId": 31,
        "township": "Rusanesti",
        "name": "Jieni",
        "isActive": 1
    },
    {
        "regionId": 31,
        "township": "Samburesti",
        "name": "Cerbeni",
        "isActive": 1
    },
    {
        "regionId": 31,
        "township": "Samburesti",
        "name": "Ionicesti",
        "isActive": 1
    },
    {
        "regionId": 31,
        "township": "Samburesti",
        "name": "Launele",
        "isActive": 1
    },
    {
        "regionId": 31,
        "township": "Samburesti",
        "name": "Manulesti",
        "isActive": 1
    },
    {
        "regionId": 31,
        "township": "Samburesti",
        "name": "Stanuleasa",
        "isActive": 1
    },
    {
        "regionId": 31,
        "township": "Samburesti",
        "name": "Tonesti",
        "isActive": 1
    },
    {
        "regionId": 31,
        "township": "Scarisoara",
        "name": "Plaviceni",
        "isActive": 1
    },
    {
        "regionId": 31,
        "township": "Scarisoara",
        "name": "Rudari",
        "isActive": 1
    },
    {
        "regionId": 31,
        "township": "Schitu",
        "name": "Catanele",
        "isActive": 1
    },
    {
        "regionId": 31,
        "township": "Schitu",
        "name": "Greci",
        "isActive": 1
    },
    {
        "regionId": 31,
        "township": "Schitu",
        "name": "Lisa",
        "isActive": 1
    },
    {
        "regionId": 31,
        "township": "Schitu",
        "name": "Mosteni",
        "isActive": 1
    },
    {
        "regionId": 31,
        "township": "Scornicesti",
        "name": "Bircii",
        "isActive": 1
    },
    {
        "regionId": 31,
        "township": "Scornicesti",
        "name": "Baltati",
        "isActive": 1
    },
    {
        "regionId": 31,
        "township": "Scornicesti",
        "name": "Chiteasca",
        "isActive": 1
    },
    {
        "regionId": 31,
        "township": "Scornicesti",
        "name": "Constantinesti",
        "isActive": 1
    },
    {
        "regionId": 31,
        "township": "Scornicesti",
        "name": "Jitaru",
        "isActive": 1
    },
    {
        "regionId": 31,
        "township": "Scornicesti",
        "name": "Mihailesti Popesti",
        "isActive": 1
    },
    {
        "regionId": 31,
        "township": "Scornicesti",
        "name": "Mogosesti",
        "isActive": 1
    },
    {
        "regionId": 31,
        "township": "Scornicesti",
        "name": "Margineni Slobozia",
        "isActive": 1
    },
    {
        "regionId": 31,
        "township": "Scornicesti",
        "name": "Negreni",
        "isActive": 1
    },
    {
        "regionId": 31,
        "township": "Scornicesti",
        "name": "Piscani",
        "isActive": 1
    },
    {
        "regionId": 31,
        "township": "Scornicesti",
        "name": "Rusciori",
        "isActive": 1
    },
    {
        "regionId": 31,
        "township": "Scornicesti",
        "name": "Teius",
        "isActive": 1
    },
    {
        "regionId": 31,
        "township": "Scornicesti",
        "name": "Suica",
        "isActive": 1
    },
    {
        "regionId": 31,
        "township": "Serbanesti",
        "name": "Strugurelu",
        "isActive": 1
    },
    {
        "regionId": 31,
        "township": "Serbanesti",
        "name": "Serbanestii de Sus",
        "isActive": 1
    },
    {
        "regionId": 31,
        "township": "Slatina",
        "name": "Cireasov",
        "isActive": 1
    },
    {
        "regionId": 31,
        "township": "Slatioara",
        "name": "Salcia",
        "isActive": 1
    },
    {
        "regionId": 31,
        "township": "Spineni",
        "name": "Alunisu",
        "isActive": 1
    },
    {
        "regionId": 31,
        "township": "Spineni",
        "name": "Cuza Voda",
        "isActive": 1
    },
    {
        "regionId": 31,
        "township": "Spineni",
        "name": "Davidesti",
        "isActive": 1
    },
    {
        "regionId": 31,
        "township": "Spineni",
        "name": "Optasani",
        "isActive": 1
    },
    {
        "regionId": 31,
        "township": "Spineni",
        "name": "Profa",
        "isActive": 1
    },
    {
        "regionId": 31,
        "township": "Spineni",
        "name": "Vineti",
        "isActive": 1
    },
    {
        "regionId": 31,
        "township": "Sprancenata",
        "name": "Barsestii de Sus",
        "isActive": 1
    },
    {
        "regionId": 31,
        "township": "Sprancenata",
        "name": "Frunzaru",
        "isActive": 1
    },
    {
        "regionId": 31,
        "township": "Sprancenata",
        "name": "Uria",
        "isActive": 1
    },
    {
        "regionId": 31,
        "township": "Stefan Cel Mare",
        "name": "Ianca Noua",
        "isActive": 1
    },
    {
        "regionId": 31,
        "township": "Strejesti",
        "name": "Colibasi",
        "isActive": 1
    },
    {
        "regionId": 31,
        "township": "Strejesti",
        "name": "Mamura",
        "isActive": 1
    },
    {
        "regionId": 31,
        "township": "Strejesti",
        "name": "Strejestii de Sus",
        "isActive": 1
    },
    {
        "regionId": 31,
        "township": "Studina",
        "name": "Arvateasca",
        "isActive": 1
    },
    {
        "regionId": 31,
        "township": "Studina",
        "name": "Gradinile",
        "isActive": 1
    },
    {
        "regionId": 31,
        "township": "Studina",
        "name": "Plaviceanca",
        "isActive": 1
    },
    {
        "regionId": 31,
        "township": "Studina",
        "name": "Studinita",
        "isActive": 1
    },
    {
        "regionId": 31,
        "township": "Tatulesti",
        "name": "Barbalai",
        "isActive": 1
    },
    {
        "regionId": 31,
        "township": "Tatulesti",
        "name": "Lunca",
        "isActive": 1
    },
    {
        "regionId": 31,
        "township": "Tatulesti",
        "name": "Mircesti",
        "isActive": 1
    },
    {
        "regionId": 31,
        "township": "Tatulesti",
        "name": "Momaiu",
        "isActive": 1
    },
    {
        "regionId": 31,
        "township": "Tatulesti",
        "name": "Magura",
        "isActive": 1
    },
    {
        "regionId": 31,
        "township": "Teslui",
        "name": "Cherlestii Mosteni",
        "isActive": 1
    },
    {
        "regionId": 31,
        "township": "Teslui",
        "name": "Cherlestii din Deal",
        "isActive": 1
    },
    {
        "regionId": 31,
        "township": "Teslui",
        "name": "Comanita",
        "isActive": 1
    },
    {
        "regionId": 31,
        "township": "Teslui",
        "name": "Corbu",
        "isActive": 1
    },
    {
        "regionId": 31,
        "township": "Teslui",
        "name": "Deleni",
        "isActive": 1
    },
    {
        "regionId": 31,
        "township": "Teslui",
        "name": "Schitu Deleni",
        "isActive": 1
    },
    {
        "regionId": 31,
        "township": "Tia Mare",
        "name": "Doanca",
        "isActive": 1
    },
    {
        "regionId": 31,
        "township": "Tia Mare",
        "name": "Potlogeni",
        "isActive": 1
    },
    {
        "regionId": 31,
        "township": "Topana",
        "name": "Cioraca",
        "isActive": 1
    },
    {
        "regionId": 31,
        "township": "Topana",
        "name": "Cojgarei",
        "isActive": 1
    },
    {
        "regionId": 31,
        "township": "Topana",
        "name": "Candelesti",
        "isActive": 1
    },
    {
        "regionId": 31,
        "township": "Topana",
        "name": "Ungureni",
        "isActive": 1
    },
    {
        "regionId": 31,
        "township": "Tufeni",
        "name": "Barza",
        "isActive": 1
    },
    {
        "regionId": 31,
        "township": "Tufeni",
        "name": "Stoborasti",
        "isActive": 1
    },
    {
        "regionId": 31,
        "township": "Urzica",
        "name": "Stavaru",
        "isActive": 1
    },
    {
        "regionId": 31,
        "township": "Vadastra",
        "name": "Visina Noua",
        "isActive": 1
    },
    {
        "regionId": 31,
        "township": "Valcele",
        "name": "Barcanesti",
        "isActive": 1
    },
    {
        "regionId": 31,
        "township": "Valcele",
        "name": "Valcelele de Sus",
        "isActive": 1
    },
    {
        "regionId": 31,
        "township": "Valea Mare",
        "name": "Barca",
        "isActive": 1
    },
    {
        "regionId": 31,
        "township": "Valea Mare",
        "name": "Recea",
        "isActive": 1
    },
    {
        "regionId": 31,
        "township": "Valea Mare",
        "name": "Turia",
        "isActive": 1
    },
    {
        "regionId": 31,
        "township": "Valea Mare",
        "name": "Zorleasca",
        "isActive": 1
    },
    {
        "regionId": 31,
        "township": "Valeni",
        "name": "Mandra",
        "isActive": 1
    },
    {
        "regionId": 31,
        "township": "Valeni",
        "name": "Popesti",
        "isActive": 1
    },
    {
        "regionId": 31,
        "township": "Valeni",
        "name": "Tirisneag",
        "isActive": 1
    },
    {
        "regionId": 31,
        "township": "Verguleasa",
        "name": "Cucueti",
        "isActive": 1
    },
    {
        "regionId": 31,
        "township": "Verguleasa",
        "name": "Cazanesti",
        "isActive": 1
    },
    {
        "regionId": 31,
        "township": "Verguleasa",
        "name": "Dumitresti",
        "isActive": 1
    },
    {
        "regionId": 31,
        "township": "Verguleasa",
        "name": "Poganu",
        "isActive": 1
    },
    {
        "regionId": 31,
        "township": "Verguleasa",
        "name": "Valea Fetei",
        "isActive": 1
    },
    {
        "regionId": 31,
        "township": "Verguleasa",
        "name": "Vanesti",
        "isActive": 1
    },
    {
        "regionId": 31,
        "township": "Vitomiresti",
        "name": "Bulimanu",
        "isActive": 1
    },
    {
        "regionId": 31,
        "township": "Vitomiresti",
        "name": "Dejesti",
        "isActive": 1
    },
    {
        "regionId": 31,
        "township": "Vitomiresti",
        "name": "Donesti",
        "isActive": 1
    },
    {
        "regionId": 31,
        "township": "Vitomiresti",
        "name": "Stanuleasa",
        "isActive": 1
    },
    {
        "regionId": 31,
        "township": "Vitomiresti",
        "name": "Trepteni",
        "isActive": 1
    },
    {
        "regionId": 31,
        "township": "Vladila",
        "name": "Frasinet Gara",
        "isActive": 1
    },
    {
        "regionId": 31,
        "township": "Vladila",
        "name": "Vladila Noua",
        "isActive": 1
    },
    {
        "regionId": 31,
        "township": "Voineasa",
        "name": "Blaj",
        "isActive": 1
    },
    {
        "regionId": 31,
        "township": "Voineasa",
        "name": "Margaritesti",
        "isActive": 1
    },
    {
        "regionId": 31,
        "township": "Voineasa",
        "name": "Racovita",
        "isActive": 1
    },
    {
        "regionId": 31,
        "township": "Voineasa",
        "name": "Rusanestii de Sus",
        "isActive": 1
    },
    {
        "regionId": 31,
        "township": "Vulpeni",
        "name": "Cotorbesti",
        "isActive": 1
    },
    {
        "regionId": 31,
        "township": "Vulpeni",
        "name": "Gropsani",
        "isActive": 1
    },
    {
        "regionId": 31,
        "township": "Vulpeni",
        "name": "Mardale",
        "isActive": 1
    },
    {
        "regionId": 31,
        "township": "Vulpeni",
        "name": "Pescaresti",
        "isActive": 1
    },
    {
        "regionId": 31,
        "township": "Vulpeni",
        "name": "Plopsorelu",
        "isActive": 1
    },
    {
        "regionId": 31,
        "township": "Vulpeni",
        "name": "Prisaca",
        "isActive": 1
    },
    {
        "regionId": 31,
        "township": "Vulpeni",
        "name": "Simniceni",
        "isActive": 1
    },
    {
        "regionId": 31,
        "township": "Vulpeni",
        "name": "Tabaci",
        "isActive": 1
    },
    {
        "regionId": 31,
        "township": "Vulpeni",
        "name": "Valea Satului",
        "isActive": 1
    },
    {
        "regionId": 31,
        "township": "Vulturesti",
        "name": "Dienci",
        "isActive": 1
    },
    {
        "regionId": 31,
        "township": "Vulturesti",
        "name": "Valea lui Alb",
        "isActive": 1
    },
    {
        "regionId": 31,
        "township": "Vulturesti",
        "name": "Vlangaresti",
        "isActive": 1
    }
]
